linux_profile_plugin/__init__.py
linux_profile_plugin/commands.py
linux_profile_plugin/main.py
linuxp_plugin-1.0.3.dist-info/LICENSE
linuxp_plugin-1.0.3.dist-info/METADATA
linuxp_plugin-1.0.3.dist-info/WHEEL
linuxp_plugin-1.0.3.dist-info/entry_points.txt
linuxp_plugin-1.0.3.dist-info/top_level.txt
linuxp_plugin-1.0.3.dist-info/zip-safe
linuxp_plugin-1.0.3.dist-info/RECORD
