Metadata-Version: 2.1
Name: linuxp-plugin
Version: 1.0.3
Summary: 🐧 Plugin Linux Profile
Home-page: https://github.com/linux-profile/linux-profile-plugin
Author: Fernando Celmer
Author-email: email@fernandocelmer.com
Classifier: Development Status :: 4 - Beta
Classifier: Operating System :: OS Independent
Classifier: License :: OSI Approved :: MIT License
Classifier: Intended Audience :: Developers
Classifier: Natural Language :: English
Classifier: Programming Language :: Python :: 3.6
Classifier: Programming Language :: Python :: 3.7
Classifier: Programming Language :: Python :: 3.8
Classifier: Programming Language :: Python :: 3.9
Classifier: Programming Language :: Python :: 3.10
Classifier: Programming Language :: Python :: 3.11
Requires-Python: >=3.6
License-File: LICENSE
Requires-Dist: linuxp (>=1.0.18)
